netsnoop
netsnoop_env
