Metadata-Version: 2.4
Name: netsnoop-monitor
Version: 0.2.0
Summary: Comprehensive system monitoring with 5 anomaly detectors
Home-page: https://github.com/yourusername/netsnoop-monitor
Author: Your Name
Author-email: Your Name <your.email@example.com>
License: MIT
Project-URL: Homepage, https://github.com/yourusername/netsnoop-monitor
Project-URL: Documentation, https://github.com/yourusername/netsnoop-monitor/blob/main/README.md
Project-URL: Repository, https://github.com/yourusername/netsnoop-monitor
Project-URL: Issues, https://github.com/yourusername/netsnoop-monitor/issues
Keywords: monitoring,system-monitor,anomaly-detection
Classifier: Development Status :: 4 - Beta
Classifier: Intended Audience :: Developers
Classifier: Topic :: System :: Monitoring
Classifier: License :: OSI Approved :: MIT License
Classifier: Programming Language :: Python :: 3
Classifier: Programming Language :: Python :: 3.8
Classifier: Programming Language :: Python :: 3.9
Classifier: Programming Language :: Python :: 3.10
Classifier: Programming Language :: Python :: 3.11
Requires-Python: >=3.8
License-File: LICENSE
Requires-Dist: psutil>=5.9.0
Requires-Dist: streamlit>=1.20.0
Requires-Dist: plotly>=5.13.0
Requires-Dist: pandas>=1.5.0
Provides-Extra: dev
Requires-Dist: pytest>=7.0.0; extra == "dev"
Requires-Dist: black>=22.0.0; extra == "dev"
Requires-Dist: flake8>=4.0.0; extra == "dev"
Dynamic: author
Dynamic: home-page
Dynamic: license-file
Dynamic: requires-python
